cpix/__init__.py
cpix/base.py
cpix/content_key.py
cpix/cpix.py
cpix/delivery_data.py
cpix/drm_system.py
cpix/filters.py
cpix/period.py
cpix/usage_rule.py
cpix/drm/__init__.py
cpix/drm/playready.py
cpix/drm/widevine.py
cpix/drm/widevine_pb2.py
cpix/schema/cpix.xsd
cpix/schema/pskc.xsd
cpix/schema/xenc-schema.xsd
cpix/schema/xmldsig-core-schema.xsd
cpix-1.4.1.dist-info/LICENSE
cpix-1.4.1.dist-info/METADATA
cpix-1.4.1.dist-info/WHEEL
cpix-1.4.1.dist-info/top_level.txt
cpix-1.4.1.dist-info/RECORD
