Metadata-Version: 2.1
Name: cpix
Version: 1.4.1
Summary: CPIX
Home-page: https://github.com/unifiedstreaming/pycpix
Author: Mark Ogle
Author-email: mark@unified-streaming.com
License-File: LICENSE
Requires-Dist: construct>=2.9.45
Requires-Dist: lxml>=4.2.3
Requires-Dist: protobuf>=3.20.0
Requires-Dist: pycryptodome>=3.6.4
Requires-Dist: requests>=2.19.1
Requires-Dist: isodate>=0.6.0
Requires-Dist: setuptools<71.0.0
